Metadata-Version: 2.1
Name: tap-exchangeratesapi
Version: 0.1.1
Summary: Singer.io tap for extracting currency exchange rate data from the exchangeratesapi.io API
Home-page: http://github.com/singer-io/tap-exchangeratesapi
Author: Stitch
License: UNKNOWN
Platform: UNKNOWN
Classifier: Programming Language :: Python :: 3 :: Only
Provides-Extra: dev
